tyler/__init__.py
tyler/forms.py
tyler/models.py
tyler/urls.py
tyler/version.py
tyler/views.py
tyler-0.1.4.dist-info/DESCRIPTION.rst
tyler-0.1.4.dist-info/METADATA
tyler-0.1.4.dist-info/pydist.json
tyler-0.1.4.dist-info/RECORD
tyler-0.1.4.dist-info/top_level.txt
tyler-0.1.4.dist-info/WHEEL
