Metadata-Version: 2.0
Name: tyler
Version: 0.1.4
Summary: Python webservice for tiling static maps
Home-page: UNKNOWN
Author: Ben Cardy
Author-email: benbacardi@gmail.com
License: UNKNOWN
Platform: UNKNOWN
Classifier: Development Status :: 3 - Alpha
Classifier: Intended Audience :: Developers
Classifier: License :: OSI Approved :: GNU General Public License v3 or later (GPLv3+)
Classifier: Framework :: Django
Classifier: Programming Language :: Python
Classifier: Programming Language :: Python :: 2
Classifier: Programming Language :: Python :: 2.7
Requires-Dist: django
Requires-Dist: requests
Requires-Dist: Pillow
